requests_fortified/__init__.py
requests_fortified/requests_fortified.py
requests_fortified/requests_fortified_download.py
requests_fortified/requests_fortified_upload.py
requests_fortified/errors/__init__.py
requests_fortified/errors/error_codes.py
requests_fortified/errors/error_desc.py
requests_fortified/errors/errors_traceback.py
requests_fortified/exceptions/__init__.py
requests_fortified/exceptions/base.py
requests_fortified/exceptions/custom.py
requests_fortified/support/__init__.py
requests_fortified/support/bom_encoding.py
requests_fortified/support/constants.py
requests_fortified/support/curl.py
requests_fortified/support/metrics.py
requests_fortified/support/requests_session_client.py
requests_fortified/support/retry_exception.py
requests_fortified/support/usage.py
requests_fortified/support/utils.py
requests_fortified/support/response/__init__.py
requests_fortified/support/response/csv.py
requests_fortified/support/response/parse.py
requests_fortified/support/response/validate.py
requests_fortified-0.3.1.dist-info/METADATA
requests_fortified-0.3.1.dist-info/RECORD
requests_fortified-0.3.1.dist-info/WHEEL
requests_fortified-0.3.1.dist-info/top_level.txt
