Metadata-Version: 2.1
Name: requests-fortified
Version: 0.3.1
Summary: Extension of Python HTTP `requests` with verbose logging using `logging-fortified`.
Home-page: https://github.com/jeff00seattle/requests-fortified
Author: UNKNOWN
Author-email: UNKNOWN
License: MIT License
Download-URL: https://github.com/jeff00seattle/requests-fortified/archive/v0.3.1.tar.gz
Keywords: requests fortified
Platform: UNKNOWN
Classifier: Development Status :: 5 - Production/Stable
Classifier: Intended Audience :: Developers
Classifier: Natural Language :: English
Classifier: License :: OSI Approved :: MIT License
Classifier: Programming Language :: Python
Classifier: Programming Language :: Python :: 3.3
Classifier: Programming Language :: Python :: 3.4
Classifier: Programming Language :: Python :: 3.5
Classifier: Programming Language :: Python :: 3.6
Classifier: Programming Language :: Python :: Implementation :: PyPy
Requires-Dist: beautifulsoup4 (>=4.5.3)
Requires-Dist: DateTime (>=4.1.1)
Requires-Dist: deepdiff (>=3.3.0)
Requires-Dist: logging-fortified (>=0.1.0)
Requires-Dist: pprintpp (>=0.3.0)
Requires-Dist: psutil (>=5.0.1)
Requires-Dist: pyhttpstatus-utils (==0.3.3)
Requires-Dist: pymemcache-client (==0.3.2)
Requires-Dist: pytest-cov (>=2.5.1)
Requires-Dist: pytest-flask (>=0.10.0)
Requires-Dist: pytest-forked (>=0.2)
Requires-Dist: pytest-httpbin (>=0.3.0)
Requires-Dist: pytest-mock (>=1.10.0)
Requires-Dist: pytest-xdist (>=1.22.2)
Requires-Dist: pytest (>=3.5.1)
Requires-Dist: python-dateutil (>=2.6.0)
Requires-Dist: requests-mock (>=1.4.0)
Requires-Dist: requests-toolbelt (>=0.8.0)
Requires-Dist: requests (>=2.18.4)
Requires-Dist: safe-cast (>=0.3.0)
Requires-Dist: six (>=1.10.0)
Requires-Dist: tzlocal (>=1.3)
Requires-Dist: ujson (>=1.35)
Requires-Dist: wheel (>=0.29.0)
Requires-Dist: xmltodict (>=0.10.2)
